missandei
