Metadata-Version: 1.0
Name: missandei
Version: 0.2.0
Summary: A dict to dict translation framework
Home-page: http://github.com/gamechanger/missandei
Author: Tom Leach
Author-email: tom@gc.io
License: MIT
Keywords: dict transformation translation
Platform: UNKNOWN
